ipv8_rust_tunnels-0.1.44.dist-info/METADATA
ipv8_rust_tunnels-0.1.44.dist-info/WHEEL
ipv8_rust_tunnels-0.1.44.dist-info/licenses/LICENSE
ipv8_rust_tunnels/__init__.py
ipv8_rust_tunnels/endpoint.py
ipv8_rust_tunnels/rust_endpoint.cpython-313-i386-linux-gnu.so
ipv8_rust_tunnels/tests/test_tunnel_community.py
ipv8_rust_tunnels-0.1.44.dist-info/RECORD
