Metadata-Version: 2.4
Name: ipv8-rust-tunnels
Version: 0.1.44
Classifier: Programming Language :: Rust
Classifier: Programming Language :: Python :: Implementation :: CPython
Classifier: Programming Language :: Python :: Implementation :: PyPy
License-File: LICENSE
Summary: IPv8 tunnel performance enhancements
Requires-Python: >=3.9
Project-URL: homepage, https://github.com/Tribler/ipv8-rust-tunnels
